examples/observability_demo.py
pypix_api/__init__.py
pypix_api/error_handling.py
pypix_api/logging.py
pypix_api/metrics.py
pypix_api/observability.py
pypix_api/py.typed
pypix_api/auth/mtls.py
pypix_api/auth/oauth2.py
pypix_api/banks/base.py
pypix_api/banks/bb.py
pypix_api/banks/exceptions.py
pypix_api/banks/sicoob.py
pypix_api/banks/methods/__init__.py
pypix_api/banks/methods/base_protocol.py
pypix_api/banks/methods/cob_methods.py
pypix_api/banks/methods/cobr_methods.py
pypix_api/banks/methods/cobv_methods.py
pypix_api/banks/methods/loc_methods.py
pypix_api/banks/methods/locrec_methods.py
pypix_api/banks/methods/lotecobv_methods.py
pypix_api/banks/methods/pix_bb_methods.py
pypix_api/banks/methods/pix_methods.py
pypix_api/banks/methods/rec_methods.py
pypix_api/banks/methods/solic_rec_methods.py
pypix_api/banks/methods/webhook_cobr_methods.py
pypix_api/banks/methods/webhook_methods.py
pypix_api/banks/methods/webhook_rec_methods.py
pypix_api/models/pix.py
pypix_api/scopes/__init__.py
pypix_api/scopes/base.py
pypix_api/scopes/bb.py
pypix_api/scopes/registry.py
pypix_api/scopes/sicoob.py
pypix_api-0.8.0.dist-info/licenses/LICENSE
pypix_api-0.8.0.dist-info/METADATA
pypix_api-0.8.0.dist-info/WHEEL
pypix_api-0.8.0.dist-info/top_level.txt
pypix_api-0.8.0.dist-info/RECORD
