Metadata-Version: 2.4
Name: pypix-api
Version: 0.8.0
Summary: Biblioteca em Python para comunicação com APIs bancárias focada na integração com o PIX
Author-email: Fábio Thomaz <fabio@ladder.dev.br>
License-Expression: MIT
Project-URL: Homepage, https://github.com/laddertech/pypix-api
Project-URL: Repository, https://github.com/laddertech/pypix-api
Keywords: pix,api,banco,pagamento,brasil
Classifier: Programming Language :: Python :: 3
Classifier: Operating System :: OS Independent
Classifier: Intended Audience :: Developers
Classifier: Topic :: Software Development :: Libraries :: Python Modules
Requires-Python: >=3.10
License-File: LICENSE
Requires-Dist: requests>=2.25.1
Requires-Dist: python-dotenv>=0.15.0
Requires-Dist: requests-pkcs12>=1.25
Requires-Dist: ruff>=0.12.0
Provides-Extra: dev
Requires-Dist: pytest>=7.0.0; extra == "dev"
Requires-Dist: pytest-mock>=3.6.1; extra == "dev"
Requires-Dist: pytest-cov>=4.0.0; extra == "dev"
Requires-Dist: pytest-xdist>=3.0.0; extra == "dev"
Requires-Dist: pytest-html>=3.1.0; extra == "dev"
Requires-Dist: pytest-benchmark>=4.0.0; extra == "dev"
Requires-Dist: build>=1.2.2.post1; extra == "dev"
Requires-Dist: twine>=6.1.0; extra == "dev"
Requires-Dist: pre-commit>=3.7.0; extra == "dev"
Requires-Dist: mypy>=1.9.0; extra == "dev"
Requires-Dist: bandit[toml]>=1.7.8; extra == "dev"
Requires-Dist: types-requests>=2.31.0; extra == "dev"
Requires-Dist: tox>=4.0.0; extra == "dev"
Requires-Dist: tox-gh-actions>=3.1.0; extra == "dev"
Provides-Extra: docs
Requires-Dist: sphinx>=7.0.0; extra == "docs"
Requires-Dist: sphinx-rtd-theme>=2.0.0; extra == "docs"
Requires-Dist: sphinx-autodoc-typehints>=1.25.0; extra == "docs"
Requires-Dist: myst-parser>=2.0.0; extra == "docs"
Requires-Dist: sphinx-copybutton>=0.5.2; extra == "docs"
Requires-Dist: linkify-it-py>=2.0.0; extra == "docs"
Dynamic: license-file
